thoth/buildlog_parser/__init__.py
thoth/buildlog_parser/cli.py
thoth/buildlog_parser/exceptions.py
thoth/buildlog_parser/parsing.py
thoth/buildlog_parser/py.typed
thoth_buildlog_parser-0.1.0.dist-info/METADATA
thoth_buildlog_parser-0.1.0.dist-info/RECORD
thoth_buildlog_parser-0.1.0.dist-info/WHEEL
thoth_buildlog_parser-0.1.0.dist-info/entry_points.txt
thoth_buildlog_parser-0.1.0.dist-info/top_level.txt
