Metadata-Version: 2.1
Name: thoth-buildlog-parser
Version: 0.1.0
Summary: Transform unstructured build logs into a structured representation
Home-page: https://github.com/thoth-station/buildlog-parser
Author: Fridolin Pokorny
Author-email: fridolin@redhat.com
License: GPLv3+
Download-URL: https://pypi.org/project/thoth-buildlog-parser
Platform: UNKNOWN
Requires-Dist: thoth-common
Requires-Dist: thoth-analyzer
Requires-Dist: attrs
Requires-Dist: pyyaml
